{"_id":{"$oid":"6400b5835cd8f673e440081e"},"name":"sojibdasmain","email":"sojibmain100","password":"sojib1","children":[{"name":"sojibdasmain","email":"sojibmain0","password":"$2a$10$cXvFqM5f11t6ZnYEjqaoc.0q1qkqij5Pkmu.uXNXA9jeaMlrwoVKa","children":[{"name":"sojibdasmain","email":"sojibmain0","password":"$2a$10$QdN8hESasSKlyMPuuKHSGeHV6K5qovH82XYJv6A8T/y.QbRtk2r8u","_id":{"$oid":"640224053989bf7e2ded5586"}},{"name":"sojibdasmain","email":"sojibmain1","password":"$2a$10$iLKTxPR1twbKjQgDU3Vgeue.jseLTVKXweKeTVHFDBsLousClATKG","_id":{"$oid":"640224283989bf7e2ded558e"}},{"name":"sojibdasmain","email":"sojibmain1","password":"$2a$10$e5F33uvTaj95Y3CGrZdjlu3Wb5vOEiYD2J9qMM3bqcG/vcGANReia","_id":{"$oid":"640224593989bf7e2ded5597"}},{"name":"sojibdasmain","email":"sojibmain1","password":"$2a$10$J47wujVrz2rCsdoIhXubrepXFYeCS3eGr6KfoWy/w2lqBI5wvLBUO","_id":{"$oid":"6402245b3989bf7e2ded55a1"}}],"_id":{"$oid":"640224013989bf7e2ded5570"}},{"name":"sojibdasmain","email":"sojibmain0","password":"$2a$10$WE4S8MskeRD8gWxUdLGCqOFqRXT99EXQc9tNMdzKkdedzLk6gVLku","children":[{"name":"sojibdasmain","email":"sojibmain1","password":"$2a$10$PyzuRVCKnRqMjYGE.ucVqeTdxulxeod.npWSxdA1Sm84Wl5hhi6h6","_id":{"$oid":"6402245c3989bf7e2ded55ac"}},{"name":"sojibdasmain","email":"sojibmain2","password":"$2a$10$1LRsHNVphq4FfocanQNm7O37eKmFYuiwaNiwy/xIfjxxyUxTmY2bG","_id":{"$oid":"640224613989bf7e2ded55b8"}},{"name":"sojibdasmain","email":"sojibmain2","password":"$2a$10$h/DoKGonEBayEpboCOLga.HpN3YJ864YQFfFaEvTRmnpqXjdWWpXa","_id":{"$oid":"640224623989bf7e2ded55c5"}},{"name":"sojibdasmain","email":"sojibmain2","password":"$2a$10$sQ18GNPv2aqYiHuTjcZFMeStpYLRmIPwin0qWHbiyoW6faEBDRhwW","_id":{"$oid":"640224643989bf7e2ded55d3"}}],"_id":{"$oid":"640224023989bf7e2ded5574"}},{"name":"sojibdasmain","email":"sojibmain0","password":"$2a$10$XcrVY67sJjWOqpbhBQAiN.WVnAF6LDm2l1.4QQ.3TmpLHptjTQi/u","children":[{"name":"sojibdasmain","email":"sojibmain2","password":"$2a$10$Obzc.TBi04qlD665RtpDVOexkauUIScY87rDDk8tFunUdZppHoa3i","_id":{"$oid":"640224653989bf7e2ded55e2"}},{"name":"sojibdasmain","email":"sojibmain3","password":"$2a$10$fppdEj5iVUSDpFDcwf.hh.m5xg.CBVeY7IZap3/qBjXU0glXuyRE.","_id":{"$oid":"640224683989bf7e2ded55f2"}},{"name":"sojibdasmain","email":"sojibmain3","password":"$2a$10$jJhSQ0PGIIGttmEMDKqVO.xMpECRCYu6enTW1rBmr9hDD9lDVpCVG","_id":{"$oid":"6402246a3989bf7e2ded5603"}},{"name":"sojibdasmain","email":"sojibmain3","password":"$2a$10$BJtAFx401l3noKdjzwDqeeXc9dmBk7Kx2OtyEPO40S0QMmta9Rj56","_id":{"$oid":"6402246b3989bf7e2ded5615"}}],"_id":{"$oid":"640224033989bf7e2ded5579"}},{"name":"sojibdasmain","email":"sojibmain0","password":"$2a$10$Qn7JJE1KawupGF.5qLn8GulbXpyYV5KXLSpFVqt7qKF5xi/RGvl5u","children":[{"name":"sojibdasmain","email":"sojibmain3","password":"$2a$10$QGGx7uJiST7uYq7WiyQ2ce.i1P3es0KVNgFG/ZId2S48q4mS57f52","_id":{"$oid":"6402246c3989bf7e2ded5628"}}],"_id":{"$oid":"640224043989bf7e2ded557f"}}],"__v":{"$numberInt":"17"}}